yelp_clog-2.12.1.dist-info/metadata.json
yelp_clog-2.12.1.dist-info/DESCRIPTION.rst
yelp_clog-2.12.1.dist-info/WHEEL
yelp_clog-2.12.1.dist-info/top_level.txt
yelp_clog-2.12.1.dist-info/RECORD
yelp_clog-2.12.1.dist-info/METADATA
clog/scribe_net.py
clog/metrics_reporter.py
clog/zipkin_plugin.py
clog/loggers.py
clog/handlers.py
clog/config.py
clog/readers.py
clog/__init__.py
clog/utils.py
clog/global_state.py
clog/uwsgi_plugin.py
clog/scribe.thrift
clog/fb303.thrift
