Metadata-Version: 2.0
Name: yelp-clog
Version: 2.12.1
Summary: A package which provides logging and reading from scribe.
Home-page: UNKNOWN
Author: Yelp Infra Team
Author-email: infra@yelp.com
License: UNKNOWN
Platform: UNKNOWN
Classifier: Programming Language :: Python :: 2
Classifier: Programming Language :: Python :: 2.7
Classifier: Programming Language :: Python :: 3
Classifier: Programming Language :: Python :: 3.3
Classifier: Programming Language :: Python :: 3.4
Classifier: Programming Language :: Python :: 3.5
Classifier: Programming Language :: Python :: 3.6
Classifier: Programming Language :: Python :: Implementation :: CPython
Requires-Dist: boto (>=2.0.0)
Requires-Dist: thriftpy
Requires-Dist: PyStaticConfiguration (>=0.10.3)
Requires-Dist: simplejson
Requires-Dist: six (>=1.4.0)
Provides-Extra: internal
Requires-Dist: yelp-meteorite (>=1.3.0,<2.0.0); extra == 'internal'
Requires-Dist: monk (>=0.3.0,<0.4.0); extra == 'internal'
Provides-Extra: uwsgi
Requires-Dist: uWSGI; extra == 'uwsgi'
Provides-Extra: zipkin
Requires-Dist: py-zipkin; extra == 'zipkin'
